README.md
setup.py
dataclass_cli.egg-info/PKG-INFO
dataclass_cli.egg-info/SOURCES.txt
dataclass_cli.egg-info/dependency_links.txt
dataclass_cli.egg-info/top_level.txt
datacli/__init__.py