Metadata-Version: 2.1
Name: dataclass-cli
Version: 0.1.0
Summary: A library for building simple CLIs from dataclasses
Home-page: https://github.com/Jeremy-Stafford/datacli
Author: Jeremy Stafford
Author-email: jeremyspianopenguin@gmail.com
License: UNKNOWN
Platform: UNKNOWN
Classifier: Development Status :: 4 - Beta
Classifier: Environment :: Console
Classifier: Intended Audience :: Developers
Classifier: License :: OSI Approved :: MIT License
Classifier: Programming Language :: Python :: 3
